m_try/__init__.py
m_try/algebra.py
m_try/geometry.py
m_try-0.2.0.dist-info/METADATA
m_try-0.2.0.dist-info/WHEEL
m_try-0.2.0.dist-info/top_level.txt
m_try-0.2.0.dist-info/RECORD
